osirispy/__init__.py
osirispy/osirispy.py
osirispy-0.0.13.dist-info/METADATA
osirispy-0.0.13.dist-info/WHEEL
osirispy-0.0.13.dist-info/licenses/LICENSE
osirispy-0.0.13.dist-info/RECORD
