Metadata-Version: 2.1
Name: osirispy
Version: 0.0.13
Summary: A small package to read OSIRIS HDF5 Data in python
Project-URL: Homepage, https://github.com/pardallio/plots
Project-URL: Bug Tracker, https://github.com/pardallio/plots/issues
Author-email: Miguel Pardal <pardalmiguel@hotmail.com>
License-File: LICENSE
Classifier: License :: OSI Approved :: MIT License
Classifier: Operating System :: OS Independent
Classifier: Programming Language :: Python :: 3
Requires-Python: >=3.7
Requires-Dist: h5py>=3.7.0
Requires-Dist: numpy>=1.23.2
